chuk_session_manager/__init__.py
chuk_session_manager/exceptions.py
chuk_session_manager/infinite_conversation.py
chuk_session_manager/session_aware_tool_processor.py
chuk_session_manager/session_prompt_builder.py
chuk_session_manager/models/__init__.py
chuk_session_manager/models/event_source.py
chuk_session_manager/models/event_type.py
chuk_session_manager/models/session.py
chuk_session_manager/models/session_event.py
chuk_session_manager/models/session_metadata.py
chuk_session_manager/models/session_run.py
chuk_session_manager/models/token_usage.py
chuk_session_manager/storage/__init__.py
chuk_session_manager/storage/base.py
chuk_session_manager/storage/providers/__init__.py
chuk_session_manager/storage/providers/file.py
chuk_session_manager/storage/providers/memory.py
chuk_session_manager/storage/providers/redis.py
chuk_session_manager-0.1.0.dist-info/licenses/LICENSE.MD
chuk_session_manager-0.1.0.dist-info/METADATA
chuk_session_manager-0.1.0.dist-info/WHEEL
chuk_session_manager-0.1.0.dist-info/top_level.txt
chuk_session_manager-0.1.0.dist-info/RECORD
